{
    "sourceFile": "src/views/BedList.vue",
    "activeCommit": 0,
    "commits": [
        {
            "activePatchIndex": 15,
            "patches": [
                {
                    "date": 1735373949992,
                    "content": "Index: \n===================================================================\n--- \n+++ \n"
                },
                {
                    "date": 1735383387535,
                    "content": "Index: \n===================================================================\n--- \n+++ \n@@ -61,9 +61,9 @@\n                            size=\"small\"\n                             style=\"font-size: 18px\"\n                             type=\"danger\"\n                             @click=\"emptyDialog(scope.row.bId)\"\n-                        ><i class=\"iconfont icon-r-delete\" style=\"font-size: 22px;\"></i> 删除</el-button>\n+                        ><i class=\"iconfont icon-r-delete\" style=\"font-size: 22px;\"></i> 清空床位</el-button>\n                     </template>\n                 </el-table-column>\n             </el-table>\n \n"
                },
                {
                    "date": 1735383409391,
                    "content": "Index: \n===================================================================\n--- \n+++ \n@@ -61,9 +61,9 @@\n                            size=\"small\"\n                             style=\"font-size: 18px\"\n                             type=\"danger\"\n                             @click=\"emptyDialog(scope.row.bId)\"\n-                        ><i class=\"iconfont icon-r-delete\" style=\"font-size: 22px;\"></i> 清空床位</el-button>\n+                        > 清空床位</el-button>\n                     </template>\n                 </el-table-column>\n             </el-table>\n \n"
                },
                {
                    "date": 1735383452229,
                    "content": "Index: \n===================================================================\n--- \n+++ \n@@ -55,9 +55,9 @@\n                             style=\"font-size: 18px\"\n                             type=\"success\"\n                                size=\"small\"\n                             @click=\"deleteDialog(scope.row.bId)\"\n-                        ><i class=\"iconfont icon-r-edit\" style=\"font-size: 22px;\"></i> 编辑</el-button>\n+                        ><i class=\"iconfont icon-r-edit\" style=\"font-size: 22px;\"></i>删除</el-button>\n                         <el-button\n                            size=\"small\"\n                             style=\"font-size: 18px\"\n                             type=\"danger\"\n"
                },
                {
                    "date": 1735383480977,
                    "content": "Index: \n===================================================================\n--- \n+++ \n@@ -53,15 +53,15 @@\n                     <template slot-scope=\"scope\">\n                         <el-button\n                             style=\"font-size: 18px\"\n                             type=\"success\"\n-                               size=\"small\"\n+                               size=\"danger\"\n                             @click=\"deleteDialog(scope.row.bId)\"\n                         ><i class=\"iconfont icon-r-edit\" style=\"font-size: 22px;\"></i>删除</el-button>\n                         <el-button\n                            size=\"small\"\n                             style=\"font-size: 18px\"\n-                            type=\"danger\"\n+                            type=\"success\"\n                             @click=\"emptyDialog(scope.row.bId)\"\n                         > 清空床位</el-button>\n                     </template>\n                 </el-table-column>\n"
                },
                {
                    "date": 1735383497368,
                    "content": "Index: \n===================================================================\n--- \n+++ \n@@ -52,8 +52,9 @@\n                 <el-table-column label=\"操作\" width=\"240\" fixed=\"right\">\n                     <template slot-scope=\"scope\">\n                         <el-button\n                             style=\"font-size: 18px\"\n+                              size=\"small\"\n                             type=\"success\"\n                                size=\"danger\"\n                             @click=\"deleteDialog(scope.row.bId)\"\n                         ><i class=\"iconfont icon-r-edit\" style=\"font-size: 22px;\"></i>删除</el-button>\n"
                },
                {
                    "date": 1735383504547,
                    "content": "Index: \n===================================================================\n--- \n+++ \n@@ -53,10 +53,10 @@\n                     <template slot-scope=\"scope\">\n                         <el-button\n                             style=\"font-size: 18px\"\n                               size=\"small\"\n-                            type=\"success\"\n-                               size=\"danger\"\n+                            type=\"danger\"\n+                            \n                             @click=\"deleteDialog(scope.row.bId)\"\n                         ><i class=\"iconfont icon-r-edit\" style=\"font-size: 22px;\"></i>删除</el-button>\n                         <el-button\n                            size=\"small\"\n"
                },
                {
                    "date": 1735383530951,
                    "content": "Index: \n===================================================================\n--- \n+++ \n@@ -50,21 +50,22 @@\n                 </el-table-column>\n \n                 <el-table-column label=\"操作\" width=\"240\" fixed=\"right\">\n                     <template slot-scope=\"scope\">\n+                      \n                         <el-button\n+                           size=\"small\"\n                             style=\"font-size: 18px\"\n+                            type=\"success\"\n+                            @click=\"emptyDialog(scope.row.bId)\"\n+                        > 清空床位</el-button>\n+                        <el-button\n+                            style=\"font-size: 18px\"\n                               size=\"small\"\n                             type=\"danger\"\n                             \n                             @click=\"deleteDialog(scope.row.bId)\"\n                         ><i class=\"iconfont icon-r-edit\" style=\"font-size: 22px;\"></i>删除</el-button>\n-                        <el-button\n-                           size=\"small\"\n-                            style=\"font-size: 18px\"\n-                            type=\"success\"\n-                            @click=\"emptyDialog(scope.row.bId)\"\n-                        > 清空床位</el-button>\n                     </template>\n                 </el-table-column>\n             </el-table>\n \n"
                },
                {
                    "date": 1735383541308,
                    "content": "Index: \n===================================================================\n--- \n+++ \n@@ -63,9 +63,9 @@\n                               size=\"small\"\n                             type=\"danger\"\n                             \n                             @click=\"deleteDialog(scope.row.bId)\"\n-                        ><i class=\"iconfont icon-r-edit\" style=\"font-size: 22px;\"></i>删除</el-button>\n+                        >删除</el-button>\n                     </template>\n                 </el-table-column>\n             </el-table>\n \n"
                },
                {
                    "date": 1735383559648,
                    "content": "Index: \n===================================================================\n--- \n+++ \n@@ -61,9 +61,8 @@\n                         <el-button\n                             style=\"font-size: 18px\"\n                               size=\"small\"\n                             type=\"danger\"\n-                            \n                             @click=\"deleteDialog(scope.row.bId)\"\n                         >删除</el-button>\n                     </template>\n                 </el-table-column>\n"
                },
                {
                    "date": 1735383590661,
                    "content": "Index: \n===================================================================\n--- \n+++ \n@@ -50,9 +50,8 @@\n                 </el-table-column>\n \n                 <el-table-column label=\"操作\" width=\"240\" fixed=\"right\">\n                     <template slot-scope=\"scope\">\n-                      \n                         <el-button\n                            size=\"small\"\n                             style=\"font-size: 18px\"\n                             type=\"success\"\n"
                },
                {
                    "date": 1735383595903,
                    "content": "Index: \n===================================================================\n--- \n+++ \n@@ -58,9 +58,9 @@\n                             @click=\"emptyDialog(scope.row.bId)\"\n                         > 清空床位</el-button>\n                         <el-button\n                             style=\"font-size: 18px\"\n-                              size=\"small\"\n+                            size=\"small\"\n                             type=\"danger\"\n                             @click=\"deleteDialog(scope.row.bId)\"\n                         >删除</el-button>\n                     </template>\n"
                },
                {
                    "date": 1735383608682,
                    "content": "Index: \n===================================================================\n--- \n+++ \n@@ -60,10 +60,9 @@\n                         <el-button\n                             style=\"font-size: 18px\"\n                             size=\"small\"\n                             type=\"danger\"\n-                            @click=\"deleteDialog(scope.row.bId)\"\n-                        >删除</el-button>\n+                            @click=\"deleteDialog(scope.row.bId)\">删除</el-button>\n                     </template>\n                 </el-table-column>\n             </el-table>\n \n"
                },
                {
                    "date": 1735383632829,
                    "content": "Index: \n===================================================================\n--- \n+++ \n@@ -60,9 +60,9 @@\n                         <el-button\n                             style=\"font-size: 18px\"\n                             size=\"small\"\n                             type=\"danger\"\n-                            @click=\"deleteDialog(scope.row.bId)\">删除</el-button>\n+                            @click=\"deleteDialog(scope.row.bId)\">删除111</el-button>\n                     </template>\n                 </el-table-column>\n             </el-table>\n \n"
                },
                {
                    "date": 1735383643725,
                    "content": "Index: \n===================================================================\n--- \n+++ \n@@ -60,9 +60,9 @@\n                         <el-button\n                             style=\"font-size: 18px\"\n                             size=\"small\"\n                             type=\"danger\"\n-                            @click=\"deleteDialog(scope.row.bId)\">删除111</el-button>\n+                            @click=\"deleteDialog(scope.row.bId)\">删除</el-button>\n                     </template>\n                 </el-table-column>\n             </el-table>\n \n"
                },
                {
                    "date": 1736826242242,
                    "content": "Index: \n===================================================================\n--- \n+++ \n@@ -5,79 +5,47 @@\n             <!-- 搜索栏及增加检查 -->\n             <el-row type=\"flex\">\n                 <el-col :span=\"6\">\n                     <el-input v-model=\"query\" placeholder=\"请输入患者id查询\">\n-                        <el-button\n-                            slot=\"append\"\n-                            @click=\"requestBeds\"\n-                            style=\"font-size: 18px\"\n-                        ><i class=\"iconfont icon-r-find\" style=\"font-size: 22px;\"></i> 搜索</el-button>\n+                        <el-button slot=\"append\" @click=\"requestBeds\" style=\"font-size: 18px\"><i\n+                                class=\"iconfont icon-r-find\" style=\"font-size: 22px;\"></i> 搜索</el-button>\n                     </el-input>\n                 </el-col>\n                 <el-col :span=\"6\"></el-col>\n                 <el-col :span=\"6\">\n-                    <el-button\n-                        type=\"primary\"\n-                        style=\"font-size: 18px\"\n-                        @click=\"addFormVisible = true\"\n-                    >\n-                    <i class=\"iconfont icon-r-add\" style=\"font-size: 22px;\"></i> \n-                        增加床位</el-button\n-                    >\n+                    <el-button type=\"primary\" style=\"font-size: 18px\" @click=\"addFormVisible = true\">\n+                        <i class=\"iconfont icon-r-add\" style=\"font-size: 22px;\"></i>\n+                        增加床位</el-button>\n                 </el-col>\n             </el-row>\n             <!-- 表格 -->\n             <el-table :data=\"bedData\" stripe style=\"width: 100%\" border>\n                 <el-table-column label=\"床号\" prop=\"bId\"></el-table-column>\n                 <el-table-column label=\"患者id\" prop=\"pId\"></el-table-column>\n                 <el-table-column label=\"医生id\" prop=\"dId\"></el-table-column>\n-                <el-table-column\n-                    label=\"开始时间\"\n-                    prop=\"bStart\"\n-                ></el-table-column>\n-                <el-table-column\n-                    label=\"申请理由\"\n-                    prop=\"bReason\"\n-                ></el-table-column>\n+                <el-table-column label=\"开始时间\" prop=\"bStart\"></el-table-column>\n+                <el-table-column label=\"申请理由\" prop=\"bReason\"></el-table-column>\n                 <el-table-column label=\"状态\" prop=\"bState\">\n                     <template slot-scope=\"scope\">\n-                        <el-tag v-if=\"scope.row.bState === 1\" type=\"danger\"\n-                            >已占用</el-tag\n-                        >\n-                        <el-tag v-if=\"scope.row.bState === 0\" type=\"success\"\n-                            >空</el-tag\n-                        >\n+                        <el-tag v-if=\"scope.row.bState === 1\" type=\"danger\">已占用</el-tag>\n+                        <el-tag v-if=\"scope.row.bState === 0\" type=\"success\">空</el-tag>\n                     </template>\n                 </el-table-column>\n \n                 <el-table-column label=\"操作\" width=\"240\" fixed=\"right\">\n                     <template slot-scope=\"scope\">\n-                        <el-button\n-                           size=\"small\"\n-                            style=\"font-size: 18px\"\n-                            type=\"success\"\n-                            @click=\"emptyDialog(scope.row.bId)\"\n-                        > 清空床位</el-button>\n-                        <el-button\n-                            style=\"font-size: 18px\"\n-                            size=\"small\"\n-                            type=\"danger\"\n+                        <el-button size=\"mini\" round style=\"font-size: 18px\" type=\"success\"\n+                            @click=\"emptyDialog(scope.row.bId)\"> 清空床位</el-button>\n+                        <el-button style=\"font-size: 18px\" size=\"mini\" round type=\"danger\"\n                             @click=\"deleteDialog(scope.row.bId)\">删除</el-button>\n                     </template>\n                 </el-table-column>\n             </el-table>\n \n             <!-- 分页 -->\n-            <el-pagination\n-                @size-change=\"handleSizeChange\"\n-                @current-change=\"handleCurrentChange\"\n-                background\n-                layout=\"total, sizes, prev, pager, next, jumper\"\n-                :current-page=\"pageNumber\"\n-                :page-size=\"size\"\n-                :page-sizes=\"[1, 2, 4, 8, 16]\"\n-                :total=\"total\"\n-            >\n+            <el-pagination @size-change=\"handleSizeChange\" @current-change=\"handleCurrentChange\" background\n+                layout=\"total, sizes, prev, pager, next, jumper\" :current-page=\"pageNumber\" :page-size=\"size\"\n+                :page-sizes=\"[1, 2, 4, 8, 16]\" :total=\"total\">\n             </el-pagination>\n         </el-card>\n \n         <!-- 增加床位对话框 -->\n@@ -87,12 +55,12 @@\n                     <el-input v-model.number=\"addForm.bId\"></el-input>\n                 </el-form-item>\n             </el-form>\n             <div slot=\"footer\" class=\"dialog-footer\">\n-                <el-button @click=\"addFormVisible = false\" style=\"font-size: 18px;\"><i class=\"iconfont icon-r-left\" style=\"font-size: 20px;\"></i> 取 消</el-button>\n-                <el-button type=\"primary\" @click=\"addBed('ruleForm')\"\n-                    style=\"font-size: 18px;\"><i class=\"iconfont icon-r-yes\" style=\"font-size: 20px;\"></i> 确 定</el-button\n-                >\n+                <el-button @click=\"addFormVisible = false\" style=\"font-size: 18px;\"><i class=\"iconfont icon-r-left\"\n+                        style=\"font-size: 20px;\"></i> 取 消</el-button>\n+                <el-button type=\"primary\" @click=\"addBed('ruleForm')\" style=\"font-size: 18px;\"><i\n+                        class=\"iconfont icon-r-yes\" style=\"font-size: 20px;\"></i> 确 定</el-button>\n             </div>\n         </el-dialog>\n     </div>\n </template>\n"
                }
            ],
            "date": 1735373949992,
            "name": "Commit-0",
            "content": "<template>\n    <div>\n        <!-- 卡片 -->\n        <el-card>\n            <!-- 搜索栏及增加检查 -->\n            <el-row type=\"flex\">\n                <el-col :span=\"6\">\n                    <el-input v-model=\"query\" placeholder=\"请输入患者id查询\">\n                        <el-button\n                            slot=\"append\"\n                            @click=\"requestBeds\"\n                            style=\"font-size: 18px\"\n                        ><i class=\"iconfont icon-r-find\" style=\"font-size: 22px;\"></i> 搜索</el-button>\n                    </el-input>\n                </el-col>\n                <el-col :span=\"6\"></el-col>\n                <el-col :span=\"6\">\n                    <el-button\n                        type=\"primary\"\n                        style=\"font-size: 18px\"\n                        @click=\"addFormVisible = true\"\n                    >\n                    <i class=\"iconfont icon-r-add\" style=\"font-size: 22px;\"></i> \n                        增加床位</el-button\n                    >\n                </el-col>\n            </el-row>\n            <!-- 表格 -->\n            <el-table :data=\"bedData\" stripe style=\"width: 100%\" border>\n                <el-table-column label=\"床号\" prop=\"bId\"></el-table-column>\n                <el-table-column label=\"患者id\" prop=\"pId\"></el-table-column>\n                <el-table-column label=\"医生id\" prop=\"dId\"></el-table-column>\n                <el-table-column\n                    label=\"开始时间\"\n                    prop=\"bStart\"\n                ></el-table-column>\n                <el-table-column\n                    label=\"申请理由\"\n                    prop=\"bReason\"\n                ></el-table-column>\n                <el-table-column label=\"状态\" prop=\"bState\">\n                    <template slot-scope=\"scope\">\n                        <el-tag v-if=\"scope.row.bState === 1\" type=\"danger\"\n                            >已占用</el-tag\n                        >\n                        <el-tag v-if=\"scope.row.bState === 0\" type=\"success\"\n                            >空</el-tag\n                        >\n                    </template>\n                </el-table-column>\n\n                <el-table-column label=\"操作\" width=\"240\" fixed=\"right\">\n                    <template slot-scope=\"scope\">\n                        <el-button\n                            style=\"font-size: 18px\"\n                            type=\"success\"\n                               size=\"small\"\n                            @click=\"deleteDialog(scope.row.bId)\"\n                        ><i class=\"iconfont icon-r-edit\" style=\"font-size: 22px;\"></i> 编辑</el-button>\n                        <el-button\n                           size=\"small\"\n                            style=\"font-size: 18px\"\n                            type=\"danger\"\n                            @click=\"emptyDialog(scope.row.bId)\"\n                        ><i class=\"iconfont icon-r-delete\" style=\"font-size: 22px;\"></i> 删除</el-button>\n                    </template>\n                </el-table-column>\n            </el-table>\n\n            <!-- 分页 -->\n            <el-pagination\n                @size-change=\"handleSizeChange\"\n                @current-change=\"handleCurrentChange\"\n                background\n                layout=\"total, sizes, prev, pager, next, jumper\"\n                :current-page=\"pageNumber\"\n                :page-size=\"size\"\n                :page-sizes=\"[1, 2, 4, 8, 16]\"\n                :total=\"total\"\n            >\n            </el-pagination>\n        </el-card>\n\n        <!-- 增加床位对话框 -->\n        <el-dialog title=\"增加床位\" :visible.sync=\"addFormVisible\">\n            <el-form :model=\"addForm\" :rules=\"rules\" ref=\"ruleForm\">\n                <el-form-item label=\"床号\" prop=\"bId\" label-width=\"80px\">\n                    <el-input v-model.number=\"addForm.bId\"></el-input>\n                </el-form-item>\n            </el-form>\n            <div slot=\"footer\" class=\"dialog-footer\">\n                <el-button @click=\"addFormVisible = false\" style=\"font-size: 18px;\"><i class=\"iconfont icon-r-left\" style=\"font-size: 20px;\"></i> 取 消</el-button>\n                <el-button type=\"primary\" @click=\"addBed('ruleForm')\"\n                    style=\"font-size: 18px;\"><i class=\"iconfont icon-r-yes\" style=\"font-size: 20px;\"></i> 确 定</el-button\n                >\n            </div>\n        </el-dialog>\n    </div>\n</template>\n<script>\nimport request from \"@/utils/request.js\";\nimport { toLoad } from \"@/utils/initialize.js\";\nexport default {\n    name: \"CheckList\",\n    data() {\n        return {\n            pageNumber: 1,\n            size: 8,\n            query: \"\",\n            bedData: [],\n            total: 3,\n            addFormVisible: false,\n            addForm: {},\n            rules: {\n                bId: [\n                    { required: true, message: \"请输入床号\", trigger: \"blur\" },\n                    {\n                        type: \"number\",\n                        message: \"床号必须数字类型\",\n                        trigger: \"blur\",\n                    },\n                ],\n            },\n        };\n    },\n    methods: {\n        //清空床位操作\n        emptyBed(id) {\n            request\n                .get(\"bed/emptyBed\", {\n                    params: {\n                        bId: id,\n                    },\n                })\n                .then((res) => {\n                    this.requestBeds();\n                    console.log(res);\n                });\n        },\n        //清空对话框\n        emptyDialog(id) {\n            this.$confirm(\"此操作将清空该床位, 是否继续?\", \"提示\", {\n                confirmButtonText: \"确定\",\n                cancelButtonText: \"取消\",\n                type: \"warning\",\n            })\n                .then(() => {\n                    this.emptyBed(id);\n                    this.$message({\n                        type: \"success\",\n                        message: \"清空成功!\",\n                    });\n                })\n                .catch(() => {\n                    this.$message({\n                        type: \"info\",\n                        message: \"已取消清空\",\n                    });\n                });\n        },\n\n        //删除床位操作\n        deleteBed(id) {\n            request\n                .get(\"bed/deleteBed\", {\n                    params: {\n                        bId: id,\n                    },\n                })\n                .then((res) => {\n                    this.requestBeds();\n                    console.log(res);\n                });\n        },\n        //删除对话框\n        deleteDialog(id) {\n            this.$confirm(\"此操作将删除该床位, 是否继续?\", \"提示\", {\n                confirmButtonText: \"确定\",\n                cancelButtonText: \"取消\",\n                type: \"warning\",\n            })\n                .then(() => {\n                    this.deleteBed(id);\n                    this.$message({\n                        type: \"success\",\n                        message: \"删除成功!\",\n                    });\n                })\n                .catch(() => {\n                    this.$message({\n                        type: \"info\",\n                        message: \"已取消删除\",\n                    });\n                });\n        },\n        //点击增加确认按钮\n        addBed(formName) {\n            this.$refs[formName].validate((valid) => {\n                if (valid) {\n                    request\n                        .get(\"bed/addBed\", {\n                            params: {\n                                bId: this.addForm.bId,\n                                pId: -1,\n                                dId: -1,\n                            },\n                        })\n                        .then((res) => {\n                            if (res.data.status !== 200)\n                                return this.$message.error(\"床号或已被占用！\");\n                            this.addFormVisible = false;\n                            this.requestBeds();\n                            this.$message.success(\"增加床位成功！\");\n                            console.log(res);\n                        });\n                } else {\n                    console.log(\"error submit!!\");\n                    return false;\n                }\n            });\n        },\n        //页面大小改变时触发\n        handleSizeChange(size) {\n            this.size = size;\n            this.requestBeds();\n        },\n        //   页码改变时触发\n        handleCurrentChange(num) {\n            console.log(num);\n            this.pageNumber = num;\n            this.requestBeds();\n        },\n        // 加载检查列表\n        requestBeds() {\n            request\n                .get(\"bed/findAllBeds\", {\n                    params: {\n                        pageNumber: this.pageNumber,\n                        size: this.size,\n                        query: this.query,\n                    },\n                })\n                .then((res) => {\n                    this.bedData = res.data.data.beds;\n                    this.total = res.data.data.total;\n                    toLoad()\n                });\n        },\n    },\n    created() {\n        this.requestBeds();\n    },\n};\n</script>\n<style scoped lang=\"scss\">\n.el-table {\n    margin-top: 20px;\n    margin-bottom: 20px;\n}\n.el-form {\n    margin-top: 0;\n}\n</style>"
        }
    ]
}